motion_master_proto/__init__.py
motion_master_proto/motion_master_pb2.py
motion_master_proto-5.2.0.dist-info/METADATA
motion_master_proto-5.2.0.dist-info/WHEEL
motion_master_proto-5.2.0.dist-info/top_level.txt
motion_master_proto-5.2.0.dist-info/RECORD
