Metadata-Version: 2.1
Name: motion-master-proto
Version: 5.2.0
Summary: Protobuf API for the Synapticon Motion Master
Home-page: https://github.com/synapticon/motion-master-proto
Author: Synapticon GmbH
Author-email: support@synapticon.com
Classifier: Programming Language :: Python :: 3
Classifier: Development Status :: 3 - Alpha
Classifier: Topic :: Software Development :: Libraries
Classifier: License :: OSI Approved :: MIT License
Classifier: Operating System :: OS Independent
Requires-Dist: protobuf (<3.19.0)
